{
    "keep": {
        "days": true,
        "amount": 1
    },
    "auditLog": "C:\\Users\\Rakib\\OneDrive\\Desktop\\projects\\E-Commerce-App\\winston\\success\\.5417690acd7403a12335a4ffdb74a183bbcfe6e6-audit.json",
    "files": [
        {
            "date": 1744974184078,
            "name": "C:\\Users\\Rakib\\OneDrive\\Desktop\\projects\\E-Commerce-App\\winston\\success\\18-04-2025-17-success.log",
            "hash": "f898209c7bdb681247a48943889372298d65c1b6baf4aff7686a7d0f90b34c52"
        },
        {
            "date": 1744977739436,
            "name": "C:\\Users\\Rakib\\OneDrive\\Desktop\\projects\\E-Commerce-App\\winston\\success\\18-04-2025-18-success.log",
            "hash": "6a628e86c3dd37d4435fcabf14af4d4b615226c204fcf88d56ad949966c2f6f9"
        },
        {
            "date": 1745032278017,
            "name": "C:\\Users\\Rakib\\OneDrive\\Desktop\\projects\\E-Commerce-App\\winston\\success\\19-04-2025-09-success.log",
            "hash": "f02ebac56bc8a272a2020fbcda03add4dfdd21e08732f1b8c18e8ab147388f03"
        },
        {
            "date": 1745035285185,
            "name": "C:\\Users\\Rakib\\OneDrive\\Desktop\\projects\\E-Commerce-App\\winston\\success\\19-04-2025-10-success.log",
            "hash": "896866a7653b258ce7fd8f9b451864ddab2884bfde5ec9886d9c4478d08291eb"
        },
        {
            "date": 1745040582412,
            "name": "C:\\Users\\Rakib\\OneDrive\\Desktop\\projects\\E-Commerce-App\\winston\\success\\19-04-2025-11-success.log",
            "hash": "7db9463805c60d9804c8aa1de8e15de90e7f0ae5bde0e69ef3f173d277d46228"
        },
        {
            "date": 1745042401957,
            "name": "C:\\Users\\Rakib\\OneDrive\\Desktop\\projects\\E-Commerce-App\\winston\\success\\19-04-2025-12-success.log",
            "hash": "0ec8bcc5cee06fa4b779ced578d103dc04438675dbc324134bdcc5902a103ee6"
        },
        {
            "date": 1745050378609,
            "name": "C:\\Users\\Rakib\\OneDrive\\Desktop\\projects\\E-Commerce-App\\winston\\success\\19-04-2025-14-success.log",
            "hash": "43263e4a6a25096f68ab06608362cc763ba55f9965bfae1c0fd80ebd3bcf12d5"
        },
        {
            "date": 1745053227935,
            "name": "C:\\Users\\Rakib\\OneDrive\\Desktop\\projects\\E-Commerce-App\\winston\\success\\19-04-2025-15-success.log",
            "hash": "e30645497dc0658b7c993bd4564a08727de6663cffb13cf9b8f268b0d3cda335"
        },
        {
            "date": 1745056802147,
            "name": "C:\\Users\\Rakib\\OneDrive\\Desktop\\projects\\E-Commerce-App\\winston\\success\\19-04-2025-16-success.log",
            "hash": "8fb70faf9024da69fb8c55523170b12e6442d4dcb86cfe561e9874a928402ff9"
        },
        {
            "date": 1745060406439,
            "name": "C:\\Users\\Rakib\\OneDrive\\Desktop\\projects\\E-Commerce-App\\winston\\success\\19-04-2025-17-success.log",
            "hash": "b38bae8a3b5057752a7dd389d11b8af54daecd447c74398fc3705e520e1b9ce4"
        }
    ],
    "hashType": "sha256"
}