{
    "keep": {
        "days": true,
        "amount": 1
    },
    "auditLog": "C:\\Users\\Rakib\\OneDrive\\Desktop\\projects\\E-Commerce-App\\winston\\error\\.90d1b362cdbaf46b9c87a9f8d14599f3683503cd-audit.json",
    "files": [
        {
            "date": 1746805500737,
            "name": "C:\\Users\\Rakib\\OneDrive\\Desktop\\projects\\E-Commerce-App\\winston\\error\\09-05-2025-21-error.log",
            "hash": "77de0cb87514af53298982a1792ddbc9992c550ea3e75c83a2e0b54dd5a3a3f2"
        },
        {
            "date": 1746864818257,
            "name": "C:\\Users\\Rakib\\OneDrive\\Desktop\\projects\\E-Commerce-App\\winston\\error\\10-05-2025-14-error.log",
            "hash": "7cc8f6917328861dd64893af19d236137f215d0cc714c353c26da85c55699285"
        },
        {
            "date": 1746867611337,
            "name": "C:\\Users\\Rakib\\OneDrive\\Desktop\\projects\\E-Commerce-App\\winston\\error\\10-05-2025-15-error.log",
            "hash": "d9f68fd86119379c1351df7b70617ae2f0a294dc217a1ff0483684799e277fab"
        },
        {
            "date": 1746871200675,
            "name": "C:\\Users\\Rakib\\OneDrive\\Desktop\\projects\\E-Commerce-App\\winston\\error\\10-05-2025-16-error.log",
            "hash": "282de64eabeb00671a4947795aa0d4eb7d25309ce0ab2d4f4a4ea7d98a4d5470"
        },
        {
            "date": 1746875001947,
            "name": "C:\\Users\\Rakib\\OneDrive\\Desktop\\projects\\E-Commerce-App\\winston\\error\\10-05-2025-17-error.log",
            "hash": "9a756a8e19ed2152d7611a66dae1eb0735fcadf569d815366c6a9105eba7ee75"
        },
        {
            "date": 1746878401928,
            "name": "C:\\Users\\Rakib\\OneDrive\\Desktop\\projects\\E-Commerce-App\\winston\\error\\10-05-2025-18-error.log",
            "hash": "eebf5994bcd7fa97ad20c16077980883068ce53f5f4c982f68c8716e38147aa7"
        },
        {
            "date": 1746882059265,
            "name": "C:\\Users\\Rakib\\OneDrive\\Desktop\\projects\\E-Commerce-App\\winston\\error\\10-05-2025-19-error.log",
            "hash": "9a63002ed78183589f70acd253c020ef16c9a7fe7a7ba7fc1244c6a3ca655658"
        },
        {
            "date": 1746885955926,
            "name": "C:\\Users\\Rakib\\OneDrive\\Desktop\\projects\\E-Commerce-App\\winston\\error\\10-05-2025-20-error.log",
            "hash": "13d544d384c420d69facd14c8a31cb0044582b4e66cd8675b136c2931161ac2e"
        }
    ],
    "hashType": "sha256"
}